napari_nifti_viewer/__init__.py
napari_nifti_viewer/_nifti_loader.py
napari_nifti_viewer/_version.py
napari_nifti_viewer/_widget.py
napari_nifti_viewer/napari.yaml
napari_nifti_viewer-0.1.2.dist-info/METADATA
napari_nifti_viewer-0.1.2.dist-info/WHEEL
napari_nifti_viewer-0.1.2.dist-info/entry_points.txt
napari_nifti_viewer-0.1.2.dist-info/top_level.txt
napari_nifti_viewer-0.1.2.dist-info/RECORD
