Metadata-Version: 2.4
Name: napari-nifti-viewer
Version: 0.1.2
Summary: A comprehensive napari plugin for NIfTI file analysis and visualization
Home-page: https://github.com/yohanchiu/napari-nifti-viewer
Author: Yohanchiu
Author-email: Yohanchiu <qyhohh@163.com>
Maintainer-email: Yohanchiu <qyhohh@163.com>
License: MIT
Project-URL: Homepage, https://github.com/yohanchiu/napari-nifti-viewer
Project-URL: Bug Tracker, https://github.com/yohanchiu/napari-nifti-viewer/issues
Project-URL: Documentation, https://github.com/yohanchiu/napari-nifti-viewer/wiki
Project-URL: Source Code, https://github.com/yohanchiu/napari-nifti-viewer
Project-URL: Changelog, https://github.com/yohanchiu/napari-nifti-viewer/blob/main/CHANGELOG.md
Keywords: napari,nifti,neuroimaging,medical imaging,visualization,plugin
Classifier: Development Status :: 4 - Beta
Classifier: Framework :: napari
Classifier: Intended Audience :: Science/Research
Classifier: Intended Audience :: Healthcare Industry
Classifier: License :: OSI Approved :: MIT License
Classifier: Operating System :: OS Independent
Classifier: Programming Language :: Python :: 3
Classifier: Programming Language :: Python :: 3.8
Classifier: Programming Language :: Python :: 3.9
Classifier: Programming Language :: Python :: 3.10
Classifier: Programming Language :: Python :: 3.11
Classifier: Programming Language :: Python :: 3.12
Classifier: Topic :: Scientific/Engineering :: Medical Science Apps.
Classifier: Topic :: Scientific/Engineering :: Image Processing
Classifier: Topic :: Scientific/Engineering :: Visualization
Classifier: Topic :: Software Development :: Libraries :: Python Modules
Requires-Python: >=3.8
Requires-Dist: napari>=0.4.18
Requires-Dist: numpy>=1.21.0
Requires-Dist: nibabel>=5.2.1
Requires-Dist: qtpy>=2.0.0
Requires-Dist: magicgui>=0.7.0
Provides-Extra: dev
Requires-Dist: pytest>=7.0; extra == "dev"
Requires-Dist: pytest-cov; extra == "dev"
Requires-Dist: black; extra == "dev"
Requires-Dist: isort; extra == "dev"
Requires-Dist: flake8; extra == "dev"
Requires-Dist: pre-commit; extra == "dev"
Provides-Extra: test
Requires-Dist: pytest>=7.0; extra == "test"
Requires-Dist: pytest-cov; extra == "test"
Dynamic: author
Dynamic: home-page
Dynamic: requires-python
